discord_mcp/__init__.py
discord_mcp/server.py
mcp_discord-0.1.0.dist-info/METADATA
mcp_discord-0.1.0.dist-info/WHEEL
mcp_discord-0.1.0.dist-info/entry_points.txt
mcp_discord-0.1.0.dist-info/licenses/LICENSE
mcp_discord-0.1.0.dist-info/RECORD
