Metadata-Version: 2.4
Name: mcp-discord
Version: 0.1.0
Summary: Discord integration for Model Context Protocol
Project-URL: Homepage, https://github.com/hanweg/mcp-discord
Project-URL: Repository, https://github.com/hanweg/mcp-discord.git
Author-email: Hanweg Altimer <hanwegaltimer@outlook.com>
License: MIT License
License-File: LICENSE
Requires-Python: >=3.10
Requires-Dist: discord-py>=2.3.0
Requires-Dist: mcp>=0.1.0
